{
  "dependencies": {
    "appInsights1": {
      "secretStore": "AzureAppSettings",
      "resourceId": "/subscriptions/[parameters('subscriptionId')]/resourceGroups/[parameters('resourceGroupName')]/providers/microsoft.insights/components/fsc-app-insights",
      "type": "appInsights.azure",
      "connectionId": "APPINSIGHTS_CONNECTIONSTRING"
    },
    "storage1": {
      "secretStore": "AzureAppSettings",
      "resourceId": "/subscriptions/[parameters('subscriptionId')]/resourceGroups/[parameters('resourceGroupName')]/providers/Microsoft.Storage/storageAccounts/fscstorage",
      "type": "storage.azure",
      "connectionId": "AzureWebJobsStorage"
    }
  }
}